linguistify/__init__.py
linguistify/cleaning.py
linguistify/feature_extraction.py
linguistify-0.1.0.dist-info/METADATA
linguistify-0.1.0.dist-info/WHEEL
linguistify-0.1.0.dist-info/RECORD
