Metadata-Version: 2.1
Name: linguistify
Version: 0.1.0
Summary: A unified toolkit for advanced text processing and linguistic analysis. This package offers a comprehensive set of functions to clean, preprocess, and analyze text data, applying sophisticated linguistic techniques to enhance your text analytics workflow. Whether you're looking to clean raw text or extract detailed linguistic features, Linguistify provides the tools to transform and enrich your text data efficiently.
Home-page: https://github.com/Jal-ghamdi/linguistify
License: MIT
Author: Jal-ghamdi
Author-email: ijawaher.a.al.ghamdi@gmail.com
Requires-Python: >=3.7,<4.0
Classifier: License :: OSI Approved :: MIT License
Classifier: Programming Language :: Python :: 3
Classifier: Programming Language :: Python :: 3.7
Classifier: Programming Language :: Python :: 3.8
Classifier: Programming Language :: Python :: 3.9
Classifier: Programming Language :: Python :: 3.10
Classifier: Programming Language :: Python :: 3.11
Project-URL: Repository, https://github.com/Jal-ghamdi/linguistify
